orm_choices/__init__.py
orm_choices/core.py
orm_choices/utils/__init__.py
orm_choices/utils/currency_code.py
orm_choices-1.0.0.dist-info/METADATA
orm_choices-1.0.0.dist-info/RECORD
orm_choices-1.0.0.dist-info/WHEEL
orm_choices-1.0.0.dist-info/top_level.txt
